CLIWeb/__init__.py
CLIWeb/cliweb.py
CLIWeb-0.0.2.dist-info/LICENSE
CLIWeb-0.0.2.dist-info/METADATA
CLIWeb-0.0.2.dist-info/WHEEL
CLIWeb-0.0.2.dist-info/entry_points.txt
CLIWeb-0.0.2.dist-info/top_level.txt
CLIWeb-0.0.2.dist-info/RECORD
