Metadata-Version: 2.1
Name: CLIWeb
Version: 0.0.2
Summary: A cli-tool to performe http requests and socket connections.
Home-page: https://github.com/iiestIT/CLIWeb
Author: iiestIT
Author-email: it.iiest.de@gmail.com
License: MIT
Platform: UNKNOWN
Requires-Python: >=3.8
Requires-Dist: websockets
